pactor/__init__.py
pactor/__main__.py
pactor/_version.py
pactor/cli.py
pactor/tests/__init__.py
pactor/tests/test_pactor.py
pactor-0.1.0.dist-info/AUTHORS.rst
pactor-0.1.0.dist-info/LICENSE
pactor-0.1.0.dist-info/METADATA
pactor-0.1.0.dist-info/WHEEL
pactor-0.1.0.dist-info/entry_points.txt
pactor-0.1.0.dist-info/top_level.txt
pactor-0.1.0.dist-info/RECORD
