Metadata-Version: 2.1
Name: pactor
Version: 0.1.0
Summary: A minimalist actor framework in Python.
Home-page: https://github.com/rtoddcarlson/pactor
Author: Todd Carlson
Author-email: none@notset.com
License: MIT
Project-URL: Issue Tracker, https://github.com/rtoddcarlson/pactor/issues
Project-URL: Documentation, https://github.com/rtoddcarlson/pactor
Keywords: actor
Platform: UNKNOWN
Classifier: Development Status :: 5 - Production/Stable
Classifier: Intended Audience :: Developers
Classifier: License :: OSI Approved :: MIT License
Classifier: Operating System :: Unix
Classifier: Operating System :: POSIX
Classifier: Operating System :: Microsoft :: Windows
Classifier: Programming Language :: Python
Classifier: Programming Language :: Python :: 3.6
Classifier: Programming Language :: Python :: 3.7
Classifier: Topic :: Utilities
Requires-Python: >=3.6.*
